google2pandas/__init__.py
google2pandas/_panalysis_ga.py
google2pandas/_query_parser.py
Google2Pandas-0.2.1.dist-info/LICENSE.md
Google2Pandas-0.2.1.dist-info/METADATA
Google2Pandas-0.2.1.dist-info/WHEEL
Google2Pandas-0.2.1.dist-info/top_level.txt
Google2Pandas-0.2.1.dist-info/RECORD
