Metadata-Version: 2.1
Name: Google2Pandas
Version: 0.2.1
Summary: Google2Pandas
Home-page: https://github.com/panalysis/Google2Pandas
Author: Matt S.
Author-email: sales@panalysis.com
Maintainer: Matt S.
Maintainer-email: sales@panalysis.com
License: MIT LICENCE
Download-URL: https://github.com/DelciousHair/google2pandas/archive/0.1.0.tar.gz
Platform: UNKNOWN
Classifier: Development Status :: 4 - Beta
Classifier: Programming Language :: Python
Classifier: Programming Language :: Python :: 3
Classifier: Intended Audience :: Science/Research
Classifier: Topic :: Scientific/Engineering
Classifier: Operating System :: OS Independent
Requires-Dist: google-api-python-client
Requires-Dist: httplib2
Requires-Dist: numpy (>=1.19)
Requires-Dist: oauth2client
Requires-Dist: pandas (>=1.1)
